{
    "name": "Wealthbot\\UserBundle\\Form\\Type\\AdminProfileType",
    "line": 7,
    "short_desc": "",
    "long_desc": "",
    "hint": null,
    "tags": [],
    "namespace": "Wealthbot\\UserBundle\\Form\\Type",
    "file": "\/srv\/wealthbot\/api\/..\/src\/Wealthbot\/UserBundle\/Form\/Type\/AdminProfileType.php",
    "relative_file": null,
    "hash": "c0d6950e91aa2aef5242fef4803741606afcfea2",
    "parent": "Wealthbot\\UserBundle\\Form\\Type\\ProfileType",
    "modifiers": "Stmt_Class",
    "is_trait": false,
    "is_interface": false,
    "aliases": {
        "FormBuilderInterface": "Symfony\\Component\\Form\\FormBuilderInterface"
    },
    "errors": [],
    "interfaces": [],
    "traits": [],
    "properties": [],
    "methods": {
        "buildForm": {
            "name": "buildForm",
            "line": 9,
            "short_desc": "",
            "long_desc": "",
            "hint": null,
            "hint_desc": null,
            "tags": [],
            "modifiers": "1",
            "is_by_ref": "",
            "exceptions": [],
            "errors": [],
            "parameters": {
                "builder": {
                    "name": "builder",
                    "line": 9,
                    "short_desc": null,
                    "long_desc": null,
                    "hint": [
                        [
                            "Wealthbot\\UserBundle\\Form\\Type\\Symfony\\Component\\Form\\FormBuilderInterface",
                            false
                        ]
                    ],
                    "tags": [],
                    "modifiers": "Symfony\\Component\\Form\\FormBuilderInterface",
                    "default": null,
                    "is_by_ref": false
                },
                "options": {
                    "name": "options",
                    "line": 9,
                    "short_desc": null,
                    "long_desc": null,
                    "hint": [
                        [
                            "array",
                            false
                        ]
                    ],
                    "tags": [],
                    "modifiers": "array",
                    "default": null,
                    "is_by_ref": false
                }
            }
        }
    },
    "constants": []
}