{
    "name": "Wealthbot\\RiaBundle\\Form\\Type\\HouseholdPortfolioSettingsFormType",
    "line": 21,
    "short_desc": "",
    "long_desc": "",
    "hint": null,
    "tags": [],
    "namespace": "Wealthbot\\RiaBundle\\Form\\Type",
    "file": "\/srv\/wealthbot\/api\/..\/src\/Wealthbot\/RiaBundle\/Form\/Type\/HouseholdPortfolioSettingsFormType.php",
    "relative_file": null,
    "hash": "4048c9e6ca286729fd6b1df723858ae1e670040a",
    "parent": "Symfony\\Component\\Form\\AbstractType",
    "modifiers": "Stmt_Class",
    "is_trait": false,
    "is_interface": false,
    "aliases": {
        "EntityRepository": "Doctrine\\ORM\\EntityRepository",
        "ArrayCollection": "Doctrine\\Common\\Collections\\ArrayCollection",
        "ClientPortfolio": "Wealthbot\\ClientBundle\\Entity\\ClientPortfolio",
        "AbstractType": "Symfony\\Component\\Form\\AbstractType",
        "FormBuilderInterface": "Symfony\\Component\\Form\\FormBuilderInterface",
        "FormEvent": "Symfony\\Component\\Form\\FormEvent",
        "FormEvents": "Symfony\\Component\\Form\\FormEvents",
        "OptionsResolverInterface": "Symfony\\Component\\OptionsResolver\\OptionsResolverInterface",
        "Profile": "Wealthbot\\UserBundle\\Entity\\Profile"
    },
    "errors": [],
    "interfaces": [],
    "traits": [],
    "properties": [],
    "methods": {
        "__construct": {
            "name": "__construct",
            "line": 25,
            "short_desc": "",
            "long_desc": "",
            "hint": null,
            "hint_desc": null,
            "tags": [],
            "modifiers": "1",
            "is_by_ref": "",
            "exceptions": [],
            "errors": [],
            "parameters": {
                "em": {
                    "name": "em",
                    "line": 25,
                    "short_desc": null,
                    "long_desc": null,
                    "hint": null,
                    "tags": [],
                    "modifiers": "",
                    "default": null,
                    "is_by_ref": false
                }
            }
        },
        "buildForm": {
            "name": "buildForm",
            "line": 30,
            "short_desc": "",
            "long_desc": "",
            "hint": null,
            "hint_desc": null,
            "tags": [],
            "modifiers": "1",
            "is_by_ref": "",
            "exceptions": [],
            "errors": [],
            "parameters": {
                "builder": {
                    "name": "builder",
                    "line": 30,
                    "short_desc": null,
                    "long_desc": null,
                    "hint": [
                        [
                            "Wealthbot\\RiaBundle\\Form\\Type\\Symfony\\Component\\Form\\FormBuilderInterface",
                            false
                        ]
                    ],
                    "tags": [],
                    "modifiers": "Symfony\\Component\\Form\\FormBuilderInterface",
                    "default": null,
                    "is_by_ref": false
                },
                "options": {
                    "name": "options",
                    "line": 30,
                    "short_desc": null,
                    "long_desc": null,
                    "hint": [
                        [
                            "array",
                            false
                        ]
                    ],
                    "tags": [],
                    "modifiers": "array",
                    "default": null,
                    "is_by_ref": false
                }
            }
        },
        "onPresetData": {
            "name": "onPresetData",
            "line": 92,
            "short_desc": "",
            "long_desc": "",
            "hint": null,
            "hint_desc": null,
            "tags": [],
            "modifiers": "1",
            "is_by_ref": "",
            "exceptions": [],
            "errors": [],
            "parameters": {
                "event": {
                    "name": "event",
                    "line": 92,
                    "short_desc": null,
                    "long_desc": null,
                    "hint": [
                        [
                            "Wealthbot\\RiaBundle\\Form\\Type\\Symfony\\Component\\Form\\FormEvent",
                            false
                        ]
                    ],
                    "tags": [],
                    "modifiers": "Symfony\\Component\\Form\\FormEvent",
                    "default": null,
                    "is_by_ref": false
                }
            }
        },
        "onBindData": {
            "name": "onBindData",
            "line": 160,
            "short_desc": "",
            "long_desc": "",
            "hint": null,
            "hint_desc": null,
            "tags": [],
            "modifiers": "1",
            "is_by_ref": "",
            "exceptions": [],
            "errors": [],
            "parameters": {
                "event": {
                    "name": "event",
                    "line": 160,
                    "short_desc": null,
                    "long_desc": null,
                    "hint": [
                        [
                            "Wealthbot\\RiaBundle\\Form\\Type\\Symfony\\Component\\Form\\FormEvent",
                            false
                        ]
                    ],
                    "tags": [],
                    "modifiers": "Symfony\\Component\\Form\\FormEvent",
                    "default": null,
                    "is_by_ref": false
                }
            }
        },
        "setDefaultOptions": {
            "name": "setDefaultOptions",
            "line": 183,
            "short_desc": "",
            "long_desc": "",
            "hint": null,
            "hint_desc": null,
            "tags": [],
            "modifiers": "1",
            "is_by_ref": "",
            "exceptions": [],
            "errors": [],
            "parameters": {
                "resolver": {
                    "name": "resolver",
                    "line": 183,
                    "short_desc": null,
                    "long_desc": null,
                    "hint": [
                        [
                            "Wealthbot\\RiaBundle\\Form\\Type\\Symfony\\Component\\OptionsResolver\\OptionsResolverInterface",
                            false
                        ]
                    ],
                    "tags": [],
                    "modifiers": "Symfony\\Component\\OptionsResolver\\OptionsResolverInterface",
                    "default": null,
                    "is_by_ref": false
                }
            }
        },
        "getName": {
            "name": "getName",
            "line": 190,
            "short_desc": "",
            "long_desc": "",
            "hint": null,
            "hint_desc": null,
            "tags": [],
            "modifiers": "1",
            "is_by_ref": "",
            "exceptions": [],
            "errors": [],
            "parameters": []
        }
    },
    "constants": []
}