{
    "name": "Wealthbot\\AdminBundle\\Tests\\Model\\PortfolioInformationTest",
    "line": 19,
    "short_desc": "",
    "long_desc": "",
    "hint": null,
    "tags": [],
    "namespace": "Wealthbot\\AdminBundle\\Tests\\Model",
    "file": "\/srv\/wealthbot\/api\/..\/src\/Wealthbot\/AdminBundle\/Tests\/Model\/PortfolioInformationTest.php",
    "relative_file": null,
    "hash": "6dba26e16d5254e35b33cfbfb71e952b47da30c2",
    "parent": "PHPUnit_Framework_TestCase",
    "modifiers": "Stmt_Class",
    "is_trait": false,
    "is_interface": false,
    "aliases": {
        "Security": "Wealthbot\\AdminBundle\\Entity\\Security",
        "SecurityAssignment": "Wealthbot\\AdminBundle\\Entity\\SecurityAssignment",
        "CeModel": "Wealthbot\\AdminBundle\\Model\\CeModel",
        "CeModelEntity": "Wealthbot\\AdminBundle\\Model\\CeModelEntity",
        "PortfolioInformation": "Wealthbot\\ClientBundle\\Model\\PortfolioInformation"
    },
    "errors": [],
    "interfaces": [],
    "traits": [],
    "properties": [],
    "methods": {
        "setUp": {
            "name": "setUp",
            "line": 24,
            "short_desc": "",
            "long_desc": "",
            "hint": null,
            "hint_desc": null,
            "tags": [],
            "modifiers": "1",
            "is_by_ref": "",
            "exceptions": [],
            "errors": [],
            "parameters": []
        },
        "testSetIsQualified": {
            "name": "testSetIsQualified",
            "line": 83,
            "short_desc": "",
            "long_desc": "",
            "hint": null,
            "hint_desc": null,
            "tags": [],
            "modifiers": "1",
            "is_by_ref": "",
            "exceptions": [],
            "errors": [],
            "parameters": []
        },
        "testGetNonQualifiedModelEntities": {
            "name": "testGetNonQualifiedModelEntities",
            "line": 92,
            "short_desc": "",
            "long_desc": "",
            "hint": null,
            "hint_desc": null,
            "tags": [],
            "modifiers": "1",
            "is_by_ref": "",
            "exceptions": [],
            "errors": [],
            "parameters": []
        },
        "testGetQualifiedModelEntities": {
            "name": "testGetQualifiedModelEntities",
            "line": 99,
            "short_desc": "",
            "long_desc": "",
            "hint": null,
            "hint_desc": null,
            "tags": [],
            "modifiers": "1",
            "is_by_ref": "",
            "exceptions": [],
            "errors": [],
            "parameters": []
        },
        "testGetModelEntities": {
            "name": "testGetModelEntities",
            "line": 105,
            "short_desc": "",
            "long_desc": "",
            "hint": null,
            "hint_desc": null,
            "tags": [],
            "modifiers": "1",
            "is_by_ref": "",
            "exceptions": [],
            "errors": [],
            "parameters": []
        },
        "testGetModelEntitiesAsJson": {
            "name": "testGetModelEntitiesAsJson",
            "line": 113,
            "short_desc": "",
            "long_desc": "",
            "hint": null,
            "hint_desc": null,
            "tags": [],
            "modifiers": "1",
            "is_by_ref": "",
            "exceptions": [],
            "errors": [],
            "parameters": []
        },
        "testGetFundExpenses": {
            "name": "testGetFundExpenses",
            "line": 135,
            "short_desc": "",
            "long_desc": "",
            "hint": null,
            "hint_desc": null,
            "tags": [],
            "modifiers": "1",
            "is_by_ref": "",
            "exceptions": [],
            "errors": [],
            "parameters": []
        },
        "testGetInvestmentMarket": {
            "name": "testGetInvestmentMarket",
            "line": 144,
            "short_desc": "",
            "long_desc": "",
            "hint": null,
            "hint_desc": null,
            "tags": [],
            "modifiers": "1",
            "is_by_ref": "",
            "exceptions": [],
            "errors": [],
            "parameters": []
        },
        "testGetGenerousInvestmentMarket": {
            "name": "testGetGenerousInvestmentMarket",
            "line": 162,
            "short_desc": "",
            "long_desc": "",
            "hint": null,
            "hint_desc": null,
            "tags": [],
            "modifiers": "1",
            "is_by_ref": "",
            "exceptions": [],
            "errors": [],
            "parameters": []
        },
        "testGetAverageInvestmentMarket": {
            "name": "testGetAverageInvestmentMarket",
            "line": 182,
            "short_desc": "",
            "long_desc": "",
            "hint": null,
            "hint_desc": null,
            "tags": [],
            "modifiers": "1",
            "is_by_ref": "",
            "exceptions": [],
            "errors": [],
            "parameters": []
        },
        "testGetLowInvestmentMarket": {
            "name": "testGetLowInvestmentMarket",
            "line": 192,
            "short_desc": "",
            "long_desc": "",
            "hint": null,
            "hint_desc": null,
            "tags": [],
            "modifiers": "1",
            "is_by_ref": "",
            "exceptions": [],
            "errors": [],
            "parameters": []
        },
        "testGetForecast": {
            "name": "testGetForecast",
            "line": 212,
            "short_desc": "",
            "long_desc": "",
            "hint": null,
            "hint_desc": null,
            "tags": [],
            "modifiers": "1",
            "is_by_ref": "",
            "exceptions": [],
            "errors": [],
            "parameters": []
        }
    },
    "constants": []
}