{
    "name": "Wealthbot\\ClientBundle\\Repository\\ClientAdditionalContactRepository",
    "line": 13,
    "short_desc": "ClientAdditionalContactRepository",
    "long_desc": "This class was generated by the Doctrine ORM. Add your own custom\nrepository methods below.",
    "hint": null,
    "tags": [],
    "namespace": "Wealthbot\\ClientBundle\\Repository",
    "file": "\/srv\/wealthbot\/api\/..\/src\/Wealthbot\/ClientBundle\/Repository\/ClientAdditionalContactRepository.php",
    "relative_file": null,
    "hash": "7d16098c12a2f5ed92615a3f190ba3ecebaca32f",
    "parent": "Doctrine\\ORM\\EntityRepository",
    "modifiers": "Stmt_Class",
    "is_trait": false,
    "is_interface": false,
    "aliases": {
        "EntityRepository": "Doctrine\\ORM\\EntityRepository"
    },
    "errors": [],
    "interfaces": [],
    "traits": [],
    "properties": [],
    "methods": [],
    "constants": []
}