{
    "name": "Wealthbot\\RiaBundle\\Repository\\AdvisorCodeRepository",
    "line": 13,
    "short_desc": "AdvisorCodeRepository",
    "long_desc": "This class was generated by the Doctrine ORM. Add your own custom\nrepository methods below.",
    "hint": null,
    "tags": [],
    "namespace": "Wealthbot\\RiaBundle\\Repository",
    "file": "\/srv\/wealthbot\/api\/..\/src\/Wealthbot\/RiaBundle\/Repository\/AdvisorCodeRepository.php",
    "relative_file": null,
    "hash": "cbfb239e1a8374fb0cb64ed3bcc44f28ea238485",
    "parent": "Doctrine\\ORM\\EntityRepository",
    "modifiers": "Stmt_Class",
    "is_trait": false,
    "is_interface": false,
    "aliases": {
        "EntityRepository": "Doctrine\\ORM\\EntityRepository"
    },
    "errors": [],
    "interfaces": [],
    "traits": [],
    "properties": [],
    "methods": {
        "getAll": {
            "name": "getAll",
            "line": 19,
            "short_desc": "",
            "long_desc": "",
            "hint": [
                [
                    "array",
                    false
                ]
            ],
            "hint_desc": "",
            "tags": [],
            "modifiers": "1",
            "is_by_ref": "",
            "exceptions": [],
            "errors": [],
            "parameters": {
                "name": {
                    "name": "name",
                    "line": 19,
                    "short_desc": "",
                    "long_desc": null,
                    "hint": [
                        [
                            "null",
                            false
                        ]
                    ],
                    "tags": [],
                    "modifiers": "",
                    "default": "null",
                    "is_by_ref": false
                }
            }
        }
    },
    "constants": []
}